ytrssdl/__init__.py
ytrssdl/downloader.py
ytrssdl/main.py
yt_rss_dl-0.0.2.dist-info/METADATA
yt_rss_dl-0.0.2.dist-info/WHEEL
yt_rss_dl-0.0.2.dist-info/entry_points.txt
yt_rss_dl-0.0.2.dist-info/top_level.txt
yt_rss_dl-0.0.2.dist-info/RECORD
