Metadata-Version: 2.1
Name: yt-rss-dl
Version: 0.0.2
Summary: A YouTube RSS Video Downloader
Home-page: https://github.com/thisisawesome1994/yt-rss-dl
Author: Joannes J.A. Wyckmans
Author-email: johan.wyckmans@gmail.com
Classifier: Programming Language :: Python :: 3
Classifier: License :: OSI Approved :: MIT License
Classifier: Operating System :: OS Independent
Requires-Python: >=3.6
Requires-Dist: feedparser
Requires-Dist: yt-dlp
